{
  "timestamp": "2026-05-29T16-00-00",
  "count": 14,
  "results": [
    {
      "url": "https://x.com/Jcbabs88/status/2060401116425449773",
      "author": "@Jcbabs88",
      "content_summary": "Calls Islam a '7th century illiterate demon possessed false prophet’s heretical death pedo cult' and 'slave cult'.",
      "category": "dog_whistle",
      "severity": 4,
      "engagement_estimate": "low"
    },
    {
      "url": "https://x.com/PlainAndCommon/status/2060401012238639111",
      "author": "@PlainAndCommon",
      "content_summary": "Compares Islam to 'malignant tumors, cancer, disease'.",
      "category": "dehumanization",
      "severity": 3,
      "engagement_estimate": "low"
    },
    {
      "url": "https://x.com/tim3po/status/2060400651960512784",
      "author": "@tim3po",
      "content_summary": "Demands Japan reject Islam and 'Deport all the Muslims'.",
      "category": "direct_hatred",
      "severity": 4,
      "engagement_estimate": "low"
    },
    {
      "url": "https://x.com/KnightsTempOrg/status/2060400188557013097",
      "author": "@KnightsTempOrg",
      "content_summary": "Describes Muslims as 'invading army' and 'threat' to UK.",
      "category": "threat_narrative",
      "severity": 4,
      "engagement_estimate": "medium"
    },
    {
      "url": "https://x.com/elizabehsotner/status/2060398647129326039",
      "author": "@elizabehsotner",
      "content_summary": "Calls to 'deport all Muslims that pray in the street' and 'All Muslims must go home now'.",
      "category": "direct_hatred",
      "severity": 5,
      "engagement_estimate": "low"
    },
    {
      "url": "https://x.com/Marcus___007/status/2060398582427963594",
      "author": "@Marcus___007",
      "content_summary": "Associates Muslims with 'rape gang' and violence.",
      "category": "crime_association",
      "severity": 4,
      "engagement_estimate": "low"
    },
    {
      "url": "https://x.com/ThePainfuITruth/status/2060398567173378182",
      "author": "@ThePainfuITruth",
      "content_summary": "Wants Muslims 'eradicated' for '1400 years of rape, murder, and torture'.",
      "category": "direct_hatred",
      "severity": 5,
      "engagement_estimate": "low"
    },
    {
      "url": "https://x.com/pots_88/status/2060398465398821258",
      "author": "@pots_88",
      "content_summary": "Suggests kicking out remaining Muslims.",
      "category": "direct_hatred",
      "severity": 3,
      "engagement_estimate": "low"
    },
    {
      "url": "https://x.com/haasandy7/status/2060398260955861503",
      "author": "@haasandy7",
      "content_summary": "Claims Muslims plan dominance, calls to deport them.",
      "category": "threat_narrative",
      "severity": 4,
      "engagement_estimate": "low"
    },
    {
      "url": "https://x.com/MichaelJaco9/status/2060396813010817299",
      "author": "@MichaelJaco9",
      "content_summary": "Calls to 'deport all Muslims from America'.",
      "category": "direct_hatred",
      "severity": 5,
      "engagement_estimate": "medium"
    },
    {
      "url": "https://x.com/Gr8Vngnz/status/2060401554742509610",
      "author": "@Gr8Vngnz",
      "content_summary": "Claims Muslims commit 'genocidal rape'.",
      "category": "crime_association",
      "severity": 4,
      "engagement_estimate": "low"
    },
    {
      "url": "https://x.com/DavidSmith67123/status/2060401477797994907",
      "author": "@DavidSmith67123",
      "content_summary": "Blames Muslims for raping white girls, says 'Deport'.",
      "category": "crime_association",
      "severity": 4,
      "engagement_estimate": "low"
    },
    {
      "url": "https://x.com/your_mominlaw/status/2060401506306707602",
      "author": "@your_mominlaw",
      "content_summary": "Calls Muslims 'parasitic plague of subhumans' and calls to 'eliminate their presence'.",
      "category": "dehumanization",
      "severity": 5,
      "engagement_estimate": "low"
    },
    {
      "url": "https://x.com/funylute/status/2060401375004250622",
      "author": "@funylute",
      "content_summary": "Calls Muslim presence an 'invasion' and says 'They don't belong here'.",
      "category": "threat_narrative",
      "severity": 4,
      "engagement_estimate": "low"
    }
  ]
}