{
  "timestamp": "2026-06-03T14-00-00",
  "count": 6,
  "results": [
    {
      "url": "https://x.com/sanjayk64377835/status/2062183511855865945",
      "author": "@sanjayk64377835",
      "content_summary": "Both Muslims and Punjabis are very dangerous. They are very aggressive... Home office have responded to do deport them",
      "category": "crime_association",
      "severity": 4,
      "engagement_estimate": "low"
    },
    {
      "url": "https://x.com/LawrenceRo83222/status/2062183065993015704",
      "author": "@LawrenceRo83222",
      "content_summary": "Islam is giving free lessons in how to rape all non muslim females encouraged by their pedophile false prophet",
      "category": "crime_association",
      "severity": 5,
      "engagement_estimate": "low"
    },
    {
      "url": "https://x.com/ricrayret/status/2062182704976965965",
      "author": "@ricrayret",
      "content_summary": "Deport all Muslims... This can not be allowed to happen here",
      "category": "direct_hatred",
      "severity": 5,
      "engagement_estimate": "low"
    },
    {
      "url": "https://x.com/4lfasecurity/status/2062181354687562178",
      "author": "@4lfasecurity",
      "content_summary": "Deport DEPORT MUSLIMS",
      "category": "direct_hatred",
      "severity": 4,
      "engagement_estimate": "low"
    },
    {
      "url": "https://x.com/Pheanixs/status/2062181354687562178",
      "author": "@Pheanixs",
      "content_summary": "MUSLIM RAPE GANGS RAPING YOUNG WHITE GIRLS... LISTEN TO THE END",
      "category": "crime_association",
      "severity": 4,
      "engagement_estimate": "low"
    },
    {
      "url": "https://x.com/Koolmoe21/status/2062183716433055841",
      "author": "@Koolmoe21",
      "content_summary": "Rip the goat fu@kers out of the western world and ship them back... Islam is not compatible with the western world!",
      "category": "threat_narrative",
      "severity": 5,
      "engagement_estimate": "low"
    }
  ]
}