{
  "timestamp": "2026-06-01T04-00-00",
  "count": 10,
  "results": [
    {
      "url": "https://x.com/MikeMOct1997/status/2061302344449495230",
      "author": "@MikeMOct1997",
      "content_summary": "Muslims are a cancer that destroys all it touches.",
      "category": "dehumanization",
      "severity": 4,
      "engagement_estimate": "low"
    },
    {
      "url": "https://x.com/riteshisjack/status/2061301680822776254",
      "author": "@riteshisjack",
      "content_summary": "Islam is the biggest threat to mankind at the moment.",
      "category": "threat_narrative",
      "severity": 3,
      "engagement_estimate": "low"
    },
    {
      "url": "https://x.com/naska1438/status/2061301611343782122",
      "author": "@naska1438",
      "content_summary": "Brown Muslim savages rape white women to humiliate them.",
      "category": "crime_association",
      "severity": 5,
      "engagement_estimate": "low"
    },
    {
      "url": "https://x.com/WhiskyMAGA/status/2061301294283759666",
      "author": "@WhiskyMAGA",
      "content_summary": "Islam is a plague to the world.",
      "category": "dehumanization",
      "severity": 4,
      "engagement_estimate": "low"
    },
    {
      "url": "https://x.com/CaravelCapitan/status/2061301245827223680",
      "author": "@CaravelCapitan",
      "content_summary": "Best of luck with the Muslim invasion.",
      "category": "threat_narrative",
      "severity": 3,
      "engagement_estimate": "low"
    },
    {
      "url": "https://x.com/TigerRose808/status/2061250266658431129",
      "author": "@TigerRose808",
      "content_summary": "Deport these evil savages. Never let Muslims in.",
      "category": "direct_hatred",
      "severity": 4,
      "engagement_estimate": "low"
    },
    {
      "url": "https://x.com/bigmmma453/status/2061261371619131573",
      "author": "@bigmmma453",
      "content_summary": "Throw them all out. Most of them are Islamists.",
      "category": "direct_hatred",
      "severity": 3,
      "engagement_estimate": "low"
    },
    {
      "url": "https://x.com/StephanieR78321/status/2061244272590901337",
      "author": "@StephanieR78321",
      "content_summary": "All Islamics need deported... destroy the USA from within.",
      "category": "direct_hatred",
      "severity": 4,
      "engagement_estimate": "low"
    },
    {
      "url": "https://x.com/lisa3ap/status/2061238065746596149",
      "author": "@lisa3ap",
      "content_summary": "Deport ALL Muslims!",
      "category": "direct_hatred",
      "severity": 5,
      "engagement_estimate": "low"
    },
    {
      "url": "https://x.com/ZsForZedd/status/2061252789859131879",
      "author": "@ZsForZedd",
      "content_summary": "Islamists... like vermin or weeds in a garden.",
      "category": "dehumanization",
      "severity": 4,
      "engagement_estimate": "low"
    }
  ]
}